{
  "symbols": [
    "LTCUSDT",
    "TRUMPUSDT",
    "SOLUSDT",
    "WIFUSDT",
    "ARBUSDT",
    "AVAXUSDT",
    "SHIB1000USDT",
    "NEARUSDT",
    "ADAUSDT",
    "XRPUSDT",
    "AAVEUSDT",
    "ENAUSDT",
    "ETHUSDT",
    "BNBUSDT",
    "CHIPUSDT",
    "1000PEPEUSDT",
    "TRXUSDT",
    "SUIUSDT",
    "PENGUUSDT",
    "DOGEUSDT",
    "ORCAUSDT",
    "BTCUSDT",
    "DOTUSDT",
    "LINKUSDT",
    "TONUSDT",
    "NAORISUSDT",
    "POLUSDT"
  ],
  "deposit": 1000.0,
  "total_pnl_pct": 0,
  "wins": 0,
  "losses": 0,
  "signals_seen": 16,
  "win_rate": 0.0,
  "active_positions": {
    "TONUSDT": {
      "symbol": "TONUSDT",
      "direction": "short",
      "entry_price": 1.3402,
      "entry_time": "2026-04-29 12:45:00+00:00",
      "stop_price": 1.346901,
      "tp_price": 1.30844,
      "stop_pct": 0.5,
      "tp_pct": 2.3698,
      "size_usdt": 200.0,
      "strategy_id": 335,
      "strategy_name": "TONUSDT 1h BOTH E0.7",
      "config_version": "v3",
      "breakeven_activated": false,
      "partial_taken": false,
      "realized_pnl_pct": 0.0,
      "exit_price": 0.0,
      "exit_time": "",
      "exit_reason": "",
      "bars_held": 0
    }
  },
  "completed_trades": [],
  "last_updated": "2026-04-29T12:48:30.603784+00:00"
}